blast/__init__.py
blast/__main__.py
blast/bag_index.npy
blast/bins.txt
blast/blast.py
blast/estimator.py
blast/parser.py
blast/scaling.npz
blast/models/flux/0.0.onnx
blast/models/flux/0.1.onnx
blast/models/flux/0.2.onnx
blast/models/flux/0.3.onnx
blast/models/flux/0.4.onnx
blast/models/flux/1.0.onnx
blast/models/flux/1.1.onnx
blast/models/flux/1.2.onnx
blast/models/flux/1.3.onnx
blast/models/flux/1.4.onnx
blast/models/flux/2.0.onnx
blast/models/flux/2.1.onnx
blast/models/flux/2.2.onnx
blast/models/flux/2.3.onnx
blast/models/flux/2.4.onnx
blast/models/flux/3.0.onnx
blast/models/flux/3.1.onnx
blast/models/flux/3.2.onnx
blast/models/flux/3.3.onnx
blast/models/flux/3.4.onnx
blast/models/flux/4.0.onnx
blast/models/flux/4.1.onnx
blast/models/flux/4.2.onnx
blast/models/flux/4.3.onnx
blast/models/flux/4.4.onnx
blast/models/freq/0.0.onnx
blast/models/freq/0.1.onnx
blast/models/freq/0.2.onnx
blast/models/freq/0.3.onnx
blast/models/freq/0.4.onnx
blast/models/freq/1.0.onnx
blast/models/freq/1.1.onnx
blast/models/freq/1.2.onnx
blast/models/freq/1.3.onnx
blast/models/freq/1.4.onnx
blast/models/freq/2.0.onnx
blast/models/freq/2.1.onnx
blast/models/freq/2.2.onnx
blast/models/freq/2.3.onnx
blast/models/freq/2.4.onnx
blast/models/freq/3.0.onnx
blast/models/freq/3.1.onnx
blast/models/freq/3.2.onnx
blast/models/freq/3.3.onnx
blast/models/freq/3.4.onnx
blast/models/freq/4.0.onnx
blast/models/freq/4.1.onnx
blast/models/freq/4.2.onnx
blast/models/freq/4.3.onnx
blast/models/freq/4.4.onnx
astroblast-2.0.1.dist-info/LICENSE.txt
astroblast-2.0.1.dist-info/METADATA
astroblast-2.0.1.dist-info/WHEEL
astroblast-2.0.1.dist-info/entry_points.txt
astroblast-2.0.1.dist-info/top_level.txt
astroblast-2.0.1.dist-info/RECORD
