Metadata-Version: 2.1
Name: astroblast
Version: 2.0.1
Summary: Synchtrotron peak estimator for blazars
Author-email: Tobias Kerscher <88444139+tkerscher@users.noreply.github.com>
License: MIT
Project-URL: Homepage, https://github.com/tkerscher/blast
Keywords: blazar,synchrotron
Classifier: Development Status :: 5 - Production/Stable
Classifier: Environment :: Console
Classifier: Intended Audience :: Science/Research
Classifier: License :: OSI Approved :: MIT License
Classifier: Topic :: Scientific/Engineering :: Astronomy
Requires-Python: >=3.8
License-File: LICENSE.txt
Requires-Dist: numpy >=1.20
Requires-Dist: onnxruntime
Requires-Dist: scipy
Requires-Dist: tqdm
Provides-Extra: dev
Requires-Dist: matplotlib ; extra == 'dev'
Requires-Dist: pytorch-lightning >=2.0 ; extra == 'dev'
Requires-Dist: scikit-learn ; extra == 'dev'
Requires-Dist: seaborn ; extra == 'dev'
Requires-Dist: torch >=1.2.0 ; extra == 'dev'
